typed_env/__init__.py
typed_env/constants.py
typed_env/env.py
typed_env/errors.py
typed_env/parser.py
typed_env/typed_var.py
typed_env/util.py
py_typed_env-0.1.1.dist-info/METADATA
py_typed_env-0.1.1.dist-info/WHEEL
py_typed_env-0.1.1.dist-info/RECORD
